ondc_auth/__init__.py
ondc_auth/core.py
superondc-0.1.0.dist-info/METADATA
superondc-0.1.0.dist-info/WHEEL
superondc-0.1.0.dist-info/RECORD
