Metadata-Version: 2.1
Name: superondc
Version: 0.1.0
Summary: A package for ONDC authorization utilities.
License: MIT
Author: Ravikiran
Requires-Python: >=3.7,<4.0
Classifier: License :: OSI Approved :: MIT License
Classifier: Programming Language :: Python :: 3
Classifier: Programming Language :: Python :: 3.7
Classifier: Programming Language :: Python :: 3.8
Classifier: Programming Language :: Python :: 3.9
Classifier: Programming Language :: Python :: 3.10
Classifier: Programming Language :: Python :: 3.11
Classifier: Programming Language :: Python :: 3.12
Classifier: Programming Language :: Python :: 3.13
Requires-Dist: cryptography (>=3.4.8,<4.0.0)
Requires-Dist: pydantic (>=1.10.0,<2.0.0)
Requires-Dist: pynacl (>=1.5.0,<2.0.0)
Requires-Dist: requests (>=2.25.0,<3.0.0)
